Metadata-Version: 2.1
Name: django-auto-prefetching
Version: 0.2.11
Summary: Tools for automatically prefetching related objects in Django and Django-rest-framework
Home-page: https://github.com/GeeWee/django-auto-prefetching
Author: Gustav Wengel
Author-email: gustavwengel@gmail.com
License: MIT
Platform: UNKNOWN
Classifier: License :: OSI Approved :: MIT License
Classifier: Programming Language :: Python
Classifier: Programming Language :: Python :: 3
Classifier: Programming Language :: Python :: 3.8
Classifier: Programming Language :: Python :: 3.9
Classifier: Programming Language :: Python :: Implementation :: CPython
Classifier: Programming Language :: Python :: Implementation :: PyPy
Requires-Python: >=3.6
License-File: LICENSE
Requires-Dist: django (>=2.2)
Provides-Extra: rest_framework_integration
Requires-Dist: djangorestframework (~=3.9) ; extra == 'rest_framework_integration'
